rtl/axi_write_only/axi_write.v
module axi #(
    parameter ID_WIDTH = 4,
    parameter DATA_WIDTH = 32,
    parameter USER_WIDTH = 1
)(
    input wire clk,
    input wire rst,

    //=========================
    //AXI4 Write Address(AW) Channel
    //=========================
    input wire s_axi_awvalid,
    output wire s_axi_awready,
    input wire [31:0] s_axi_awaddr,
    input wire [2:0] s_axi_awsize,
    input wire [1:0] s_axi_awburst,
    input wire [3:0] s_axi_awcache,
    input wire [2:0] s_axi_awprot,
    input wire [ID_WIDTH-1:0] s_axi_awid,
    input wire [7:0] s_axi_awlen,
    input wire s_axi_awlock,
    //input wire [3:0] s_axi_awlen;    //AXI3
    //input wire [1:0] s_axi_awlock;   //AXI3
    input wire [3:0] s_axi_awqos,
    input wire [3:0] s_axi_awregion,
    input wire [USER_WIDTH-1:0] s_axi_awuser,

    //=========================
    //AXI4 Write Data(W) Channel
    //=========================
    input wire s_axi_wvalid,
    output wire s_axi_wready,
    input wire s_axi_wlast,
    input wire [DATA_WIDTH-1:0] s_axi_wdata,
    input wire [(DATA_WIDTH/8)-1:0] s_axi_wstrb,
    //input wire [ID_WIDTH-1:0] s_axi_wid   //AXI3
    input wire [USER_WIDTH-1:0] s_axi_wuser,

    //=========================
    //AXI4 Write Response(B) Channel
    //=========================
    output reg s_axi_bwvalid,
    input wire s_axi_bwready,
    output reg [1:0] s_axi_bresp,
    output reg [ID_WIDTH-1:0] s_axi_bid,
    output reg [USER_WIDTH-1:0] s_axi_buser,

    //=========================
    //Debug Memory Interface
    //=========================
    output wire [DATA_WIDTH-1:0] debug_memory_data,
    input wire [7:0] debug_memory_addr
);

/* ==========================
    AXI4 Write Address(AW) Channel
    ==========================
    1. rst -> aw_active = 0, s_axi_awready = 1
    2. s_axi_awvalid = 1, s_axi_awready = 1, -> aw_handshake
    3. aw_active = 1, wready = 1
    4. wait wdata channel handshake
    5. s_axi_wvalid = 1, s_axi_wready = 1, -> w_handshake
    6. 接收WDATA
    7. check WSTRB bit
    8. write byte
*/
localparam integer STRB_WIDTH = DATA_WIDTH / 8;
localparam integer MEMORY_DEPTH = 256;

reg aw_active;
reg [31:0] awaddr_reg;
reg [2:0] awsize_reg;
reg [1:0] awburst_reg;
reg [7:0] awlen_reg;
reg [ID_WIDTH-1:0] awid_reg;
reg [USER_WIDTH-1:0] awuser_reg;
reg [DATA_WIDTH-1:0] memory [0:MEMORY_DEPTH-1];
reg [7:0] boat_count;
integer i;

assign s_axi_awready = !aw_active && !s_axi_bwvalid;
assign s_axi_wready = aw_active && !s_axi_bwvalid;


assign debug_memory_data = memory[debug_memory_addr];

//AW Channel
always @(posedge clk) begin
    if (rst) begin
        aw_active <= 1'b0;
        awaddr_reg <= 32'b0;
        awsize_reg <= 3'b0;
        awburst_reg <= 2'b0;
        awlen_reg <= 8'b0;
        awid_reg <= {ID_WIDTH{1'b0}};
        awuser_reg <= {USER_WIDTH{1'b0}};

        s_axi_bwvalid <= 1'b0;
        s_axi_bresp   <= 2'b00;
        s_axi_bid     <= {ID_WIDTH{1'b0}};
        s_axi_buser   <= {USER_WIDTH{1'b0}};
    end else begin
        if (s_axi_awvalid && s_axi_awready) begin //aw handshake
            aw_active <= 1'b1;
            awaddr_reg <= s_axi_awaddr;
            awsize_reg <= s_axi_awsize;
            awburst_reg <= s_axi_awburst;
            awlen_reg <= s_axi_awlen;
            awid_reg <= s_axi_awid;
            awuser_reg <= s_axi_awuser;
        end 
    end
end

//W Channel
always @(posedge clk) begin
    if (!rst) begin
        if (s_axi_wvalid && s_axi_wready) begin
            for (i = 0; i < STRB_WIDTH; i = i + 1) begin
                if (s_axi_wstrb[i]) begin
                    memory[awaddr_reg[9:2]][i*8 +: 8] <= s_axi_wdata[i*8 +: 8];
                end
            end
        end
    end
end

//B Channel
always @(posedge clk) begin
    if (!rst) begin
        if (s_axi_bwvalid && s_axi_bwready) begin
            s_axi_bwvalid <= 1'b0;
        end

        if (s_axi_wvalid && s_axi_wready && s_axi_wlast) begin
            aw_active     <= 1'b0;
            s_axi_bwvalid <= 1'b1;
            s_axi_bresp   <= 2'b00; //OKAY
            s_axi_bid     <= awid_reg;
            s_axi_buser   <= awuser_reg;
        end
    end
end

endmodule

rtl/axi_write_only/tb_axi_write.v
`timescale 1ns/1ps

module tb_axi_write;

    localparam ID_WIDTH   = 4;
    localparam DATA_WIDTH = 32;
    localparam USER_WIDTH = 1;

    reg clk;
    reg rst;

    reg s_axi_awvalid;
    wire s_axi_awready;
    reg [31:0] s_axi_awaddr;
    reg [2:0] s_axi_awsize;
    reg [1:0] s_axi_awburst;
    reg [3:0] s_axi_awcache;
    reg [2:0] s_axi_awprot;
    reg [ID_WIDTH-1:0] s_axi_awid;
    reg [7:0] s_axi_awlen;
    reg s_axi_awlock;
    reg [3:0] s_axi_awqos;
    reg [3:0] s_axi_awregion;
    reg [USER_WIDTH-1:0] s_axi_awuser;

    reg s_axi_wvalid;
    wire s_axi_wready;
    reg s_axi_wlast;
    reg [DATA_WIDTH-1:0] s_axi_wdata;
    reg [(DATA_WIDTH/8)-1:0] s_axi_wstrb;
    reg [USER_WIDTH-1:0] s_axi_wuser;

    wire s_axi_bwvalid;
    reg s_axi_bwready;
    wire [1:0] s_axi_bresp;
    wire [ID_WIDTH-1:0] s_axi_bid;
    wire [USER_WIDTH-1:0] s_axi_buser;

    reg [7:0] debug_memory_addr;
    wire [DATA_WIDTH-1:0] debug_memory_data;

    integer errors;

    axi #(
        .ID_WIDTH(ID_WIDTH),
        .DATA_WIDTH(DATA_WIDTH),
        .USER_WIDTH(USER_WIDTH)
    ) dut (
        .clk(clk),
        .rst(rst),

        .s_axi_awvalid(s_axi_awvalid),
        .s_axi_awready(s_axi_awready),
        .s_axi_awaddr(s_axi_awaddr),
        .s_axi_awsize(s_axi_awsize),
        .s_axi_awburst(s_axi_awburst),
        .s_axi_awcache(s_axi_awcache),
        .s_axi_awprot(s_axi_awprot),
        .s_axi_awid(s_axi_awid),
        .s_axi_awlen(s_axi_awlen),
        .s_axi_awlock(s_axi_awlock),
        .s_axi_awqos(s_axi_awqos),
        .s_axi_awregion(s_axi_awregion),
        .s_axi_awuser(s_axi_awuser),

        .s_axi_wvalid(s_axi_wvalid),
        .s_axi_wready(s_axi_wready),
        .s_axi_wlast(s_axi_wlast),
        .s_axi_wdata(s_axi_wdata),
        .s_axi_wstrb(s_axi_wstrb),
        .s_axi_wuser(s_axi_wuser),

        .s_axi_bwvalid(s_axi_bwvalid),
        .s_axi_bwready(s_axi_bwready),
        .s_axi_bresp(s_axi_bresp),
        .s_axi_bid(s_axi_bid),
        .s_axi_buser(s_axi_buser),

        .debug_memory_addr(debug_memory_addr),
        .debug_memory_data(debug_memory_data)
    );

    always #5 clk = ~clk;

    task send_aw;
        input [31:0] address;
        input [7:0] burst_length;
        input [ID_WIDTH-1:0] transaction_id;
        input [USER_WIDTH-1:0] user_value;

        begin
            @(negedge clk);

            s_axi_awaddr  = address;
            s_axi_awsize  = 3'd2;
            s_axi_awburst = 2'b01;
            s_axi_awlen   = burst_length;
            s_axi_awid    = transaction_id;
            s_axi_awuser  = user_value;
            s_axi_awvalid = 1'b1;

            while (!s_axi_awready)
                @(posedge clk);

            @(posedge clk);
            #1;

            @(negedge clk);
            s_axi_awvalid = 1'b0;
        end
    endtask

    task send_w;
        input [DATA_WIDTH-1:0] data_value;
        input [(DATA_WIDTH/8)-1:0] strobe_value;
        input last_value;

        begin
            @(negedge clk);

            s_axi_wdata  = data_value;
            s_axi_wstrb  = strobe_value;
            s_axi_wlast  = last_value;
            s_axi_wvalid = 1'b1;

            while (!s_axi_wready)
                @(posedge clk);

            @(posedge clk);
            #1;

            @(negedge clk);
            s_axi_wvalid = 1'b0;
            s_axi_wlast  = 1'b0;
        end
    endtask

    task wait_for_b;
        input [1:0] expected_resp;
        input [ID_WIDTH-1:0] expected_id;
        input [USER_WIDTH-1:0] expected_user;

        begin
            while (!s_axi_bwvalid)
                @(posedge clk);

            #1;

            if (s_axi_bresp !== expected_resp) begin
                $display("ERROR: BRESP mismatch, expected %b, got %b",
                         expected_resp, s_axi_bresp);
                errors = errors + 1;
            end

            if (s_axi_bid !== expected_id) begin
                $display("ERROR: BID mismatch, expected %h, got %h",
                         expected_id, s_axi_bid);
                errors = errors + 1;
            end

            if (s_axi_buser !== expected_user) begin
                $display("ERROR: BUSER mismatch");
                errors = errors + 1;
            end

            if (s_axi_bwvalid !== 1'b1) begin
                $display("ERROR: BVALID should remain high before BREADY");
                errors = errors + 1;
            end
        end
    endtask

    task accept_b;
        begin
            @(negedge clk);
            s_axi_bwready = 1'b1;

            @(posedge clk);
            #1;

            if (s_axi_bwvalid !== 1'b0) begin
                $display("ERROR: BVALID should be cleared after B handshake");
                errors = errors + 1;
            end
        end
    endtask

    initial begin
        $dumpfile("axi_write.vcd");
        $dumpvars(0, tb_axi_write);

        clk = 1'b0;
        rst = 1'b1;
        errors = 0;

        s_axi_awvalid  = 1'b0;
        s_axi_awaddr   = 32'd0;
        s_axi_awsize   = 3'd0;
        s_axi_awburst  = 2'b00;
        s_axi_awcache  = 4'd0;
        s_axi_awprot   = 3'd0;
        s_axi_awid     = 4'd0;
        s_axi_awlen    = 8'd0;
        s_axi_awlock   = 1'b0;
        s_axi_awqos    = 4'd0;
        s_axi_awregion = 4'd0;
        s_axi_awuser   = 1'b0;

        s_axi_wvalid = 1'b0;
        s_axi_wlast  = 1'b0;
        s_axi_wdata  = 32'd0;
        s_axi_wstrb  = 4'd0;
        s_axi_wuser  = 1'b0;

        s_axi_bwready = 1'b0;

        //==================================================
        // Test 1: Reset
        //==================================================
        repeat (2) @(posedge clk);
        #1;
        rst = 1'b0;

        #1;

        if (s_axi_awready !== 1'b1) begin
            $display("ERROR: AWREADY should be high after reset");
            errors = errors + 1;
        end

        if (s_axi_bwvalid !== 1'b0) begin
            $display("ERROR: BVALID should be low after reset");
            errors = errors + 1;
        end

        //==================================================
        // Test 2: Single-beat full write
        // Address 0x40 -> memory[16]
        //==================================================
        send_aw(
            32'h0000_0040,
            8'd0,
            4'hA,
            1'b1
        );

        if (s_axi_awready !== 1'b0) begin
            $display("ERROR: AWREADY should be low while write is active");
            errors = errors + 1;
        end

        if (s_axi_wready !== 1'b1) begin
            $display("ERROR: WREADY should be high after AW handshake");
            errors = errors + 1;
        end

        send_w(
            32'hAABB_CCDD,
            4'b1111,
            1'b1
        );

        debug_memory_addr = 8'd16;
        #1;

        if (debug_memory_data !== 32'hAABB_CCDD) begin
            $display("ERROR: full write data mismatch");
            $display("       expected AABBCCDD, got %h", debug_memory_data);
            errors = errors + 1;
        end

        // BREADY is low, so BVALID must be held
        wait_for_b(2'b00, 4'hA, 1'b1);

        accept_b;

        if (s_axi_awready !== 1'b1) begin
            $display("ERROR: AWREADY should be high after B handshake");
            errors = errors + 1;
        end

        //==================================================
        // Test 3: Partial WSTRB
        // Original: 0x11223344
        // WDATA:   0xAABBCCDD
        // WSTRB:   0101
        // Result:  0x11BB33DD
        // Address 0x44 -> memory[17]
        //==================================================
        send_aw(
            32'h0000_0044,
            8'd0,
            4'h9,
            1'b0
        );

        send_w(
            32'h1122_3344,
            4'b1111,
            1'b1
        );

        wait_for_b(2'b00, 4'h9, 1'b0);
        accept_b;

        send_aw(
            32'h0000_0044,
            8'd0,
            4'hB,
            1'b0
        );

        send_w(
            32'hAABB_CCDD,
            4'b0101,
            1'b1
        );

        debug_memory_addr = 8'd17;
        #1;

        if (debug_memory_data !== 32'h11BB_33DD) begin
            $display("ERROR: partial WSTRB write mismatch");
            $display("       expected 11BB33DD, got %h", debug_memory_data);
            errors = errors + 1;
        end

        wait_for_b(2'b00, 4'hB, 1'b0);
        accept_b;

        //==================================================
        // Test 4: WLAST = 0 followed by WLAST = 1
        // Address 0x48 -> memory[18]
        //==================================================
        send_aw(
            32'h0000_0048,
            8'd1,
            4'hC,
            1'b1
        );

        send_w(
            32'h1111_2222,
            4'b1111,
            1'b0
        );

        if (s_axi_bwvalid !== 1'b0) begin
            $display("ERROR: BVALID should remain low before WLAST");
            errors = errors + 1;
        end

        if (s_axi_wready !== 1'b1) begin
            $display("ERROR: WREADY should remain high before WLAST");
            errors = errors + 1;
        end

        send_w(
            32'h3333_4444,
            4'b1111,
            1'b1
        );

        debug_memory_addr = 8'd18;
        #1;

        if (debug_memory_data !== 32'h3333_4444) begin
            $display("ERROR: second write data mismatch");
            errors = errors + 1;
        end

        wait_for_b(2'b00, 4'hC, 1'b1);
        accept_b;

        //==================================================
        // Final result
        //==================================================
        if (errors == 0) begin
            $display("PASS: AXI write testbench passed");
        end else begin
            $display("FAIL: %0d error(s)", errors);
        end

        #10;
        $finish;
    end

endmodule

rtl/axi_write_only/axi_write.vcd
$date
	Tue Sep 15 15:32:08 2026
$end
$version
	Icarus Verilog
$end
$timescale
	1ps
$end
$scope module tb_axi_write $end
$var wire 1 ! s_axi_wready $end
$var wire 1 " s_axi_bwvalid $end
$var wire 1 # s_axi_buser $end
$var wire 2 $ s_axi_bresp [1:0] $end
$var wire 4 % s_axi_bid [3:0] $end
$var wire 1 & s_axi_awready $end
$var wire 32 ' debug_memory_data [31:0] $end
$var parameter 32 ( DATA_WIDTH $end
$var parameter 32 ) ID_WIDTH $end
$var parameter 32 * USER_WIDTH $end
$var reg 1 + clk $end
$var reg 8 , debug_memory_addr [7:0] $end
$var reg 1 - rst $end
$var reg 32 . s_axi_awaddr [31:0] $end
$var reg 2 / s_axi_awburst [1:0] $end
$var reg 4 0 s_axi_awcache [3:0] $end
$var reg 4 1 s_axi_awid [3:0] $end
$var reg 8 2 s_axi_awlen [7:0] $end
$var reg 1 3 s_axi_awlock $end
$var reg 3 4 s_axi_awprot [2:0] $end
$var reg 4 5 s_axi_awqos [3:0] $end
$var reg 4 6 s_axi_awregion [3:0] $end
$var reg 3 7 s_axi_awsize [2:0] $end
$var reg 1 8 s_axi_awuser $end
$var reg 1 9 s_axi_awvalid $end
$var reg 1 : s_axi_bwready $end
$var reg 32 ; s_axi_wdata [31:0] $end
$var reg 1 < s_axi_wlast $end
$var reg 4 = s_axi_wstrb [3:0] $end
$var reg 1 > s_axi_wuser $end
$var reg 1 ? s_axi_wvalid $end
$var integer 32 @ errors [31:0] $end
$scope module dut $end
$var wire 1 + clk $end
$var wire 8 A debug_memory_addr [7:0] $end
$var wire 32 B debug_memory_data [31:0] $end
$var wire 1 - rst $end
$var wire 32 C s_axi_awaddr [31:0] $end
$var wire 2 D s_axi_awburst [1:0] $end
$var wire 4 E s_axi_awcache [3:0] $end
$var wire 4 F s_axi_awid [3:0] $end
$var wire 8 G s_axi_awlen [7:0] $end
$var wire 1 3 s_axi_awlock $end
$var wire 3 H s_axi_awprot [2:0] $end
$var wire 4 I s_axi_awqos [3:0] $end
$var wire 1 & s_axi_awready $end
$var wire 4 J s_axi_awregion [3:0] $end
$var wire 3 K s_axi_awsize [2:0] $end
$var wire 1 8 s_axi_awuser $end
$var wire 1 9 s_axi_awvalid $end
$var wire 1 : s_axi_bwready $end
$var wire 32 L s_axi_wdata [31:0] $end
$var wire 1 < s_axi_wlast $end
$var wire 1 ! s_axi_wready $end
$var wire 4 M s_axi_wstrb [3:0] $end
$var wire 1 > s_axi_wuser $end
$var wire 1 ? s_axi_wvalid $end
$var parameter 32 N DATA_WIDTH $end
$var parameter 32 O ID_WIDTH $end
$var parameter 32 P MEMORY_DEPTH $end
$var parameter 32 Q STRB_WIDTH $end
$var parameter 32 R USER_WIDTH $end
$var reg 1 S aw_active $end
$var reg 32 T awaddr_reg [31:0] $end
$var reg 2 U awburst_reg [1:0] $end
$var reg 4 V awid_reg [3:0] $end
$var reg 8 W awlen_reg [7:0] $end
$var reg 3 X awsize_reg [2:0] $end
$var reg 1 Y awuser_reg $end
$var reg 4 Z s_axi_bid [3:0] $end
$var reg 2 [ s_axi_bresp [1:0] $end
$var reg 1 # s_axi_buser $end
$var reg 1 " s_axi_bwvalid $end
$var integer 32 \ i [31:0] $end
$upscope $end
$scope task accept_b $end
$upscope $end
$scope task send_aw $end
$var reg 32 ] address [31:0] $end
$var reg 8 ^ burst_length [7:0] $end
$var reg 4 _ transaction_id [3:0] $end
$var reg 1 ` user_value $end
$upscope $end
$scope task send_w $end
$var reg 32 a data_value [31:0] $end
$var reg 1 b last_value $end
$var reg 4 c strobe_value [3:0] $end
$upscope $end
$scope task wait_for_b $end
$var reg 4 d expected_id [3:0] $end
$var reg 2 e expected_resp [1:0] $end
$var reg 1 f expected_user $end
$upscope $end
$upscope $end
$enddefinitions $end
$comment Show the parameter values. $end
$dumpall
b1 R
b100 Q
b100000000 P
b100 O
b100000 N
b1 *
b100 )
b100000 (
$end
#0
$dumpvars
xf
bx e
bx d
bx c
xb
bx a
x`
bx _
bx ^
bx ]
bx \
bx [
bx Z
xY
bx X
bx W
bx V
bx U
bx T
xS
b0 M
b0 L
b0 K
b0 J
b0 I
b0 H
b0 G
b0 F
b0 E
b0 D
b0 C
bx B
bx A
b0 @
0?
0>
b0 =
0<
b0 ;
0:
09
08
b0 7
b0 6
b0 5
b0 4
03
b0 2
b0 1
b0 0
b0 /
b0 .
1-
bx ,
0+
bx '
x&
bx %
bx $
x#
x"
x!
$end
#5000
1&
0!
0#
b0 %
b0 Z
b0 $
b0 [
0"
0Y
b0 V
b0 W
b0 U
b0 X
b0 T
0S
1+
#10000
0+
#15000
1+
#16000
0-
#17000
1`
b1010 _
b0 ^
b1000000 ]
#20000
19
18
b1010 1
b1010 F
b1 /
b1 D
b10 7
b10 K
b1000000 .
b1000000 C
0+
#25000
0&
1!
1Y
b1010 V
b1 U
b10 X
b1000000 T
1S
1+
#30000
1b
b1111 c
b10101010101110111100110011011101 a
09
0+
#35000
1+
#40000
1?
1<
b1111 =
b1111 M
b10101010101110111100110011011101 ;
b10101010101110111100110011011101 L
0+
#45000
0!
1#
b1010 %
b1010 Z
1"
0S
b100 \
1+
#50000
b10101010101110111100110011011101 '
b10101010101110111100110011011101 B
b10000 ,
b10000 A
0<
0?
0+
#51000
1f
b1010 d
b0 e
#55000
1+
#60000
1:
0+
#65000
1&
0"
1+
#66000
0`
b1001 _
b1000100 ]
#70000
19
08
b1001 1
b1001 F
b1000100 .
b1000100 C
0+
#75000
0&
1!
0Y
b1001 V
b1000100 T
1S
1+
#80000
b10001001000100011001101000100 a
09
0+
#85000
1+
#90000
1?
1<
b10001001000100011001101000100 ;
b10001001000100011001101000100 L
0+
#95000
0!
0#
b1001 %
b1001 Z
1"
0S
b100 \
1+
#100000
0f
b1001 d
0<
0?
0+
#105000
1&
0"
1+
#110000
0+
#115000
1+
#116000
b1011 _
#120000
19
b1011 1
b1011 F
0+
#125000
0&
1!
b1011 V
1S
1+
#130000
b101 c
b10101010101110111100110011011101 a
09
0+
#135000
1+
#140000
1?
1<
b101 =
b101 M
b10101010101110111100110011011101 ;
b10101010101110111100110011011101 L
0+
#145000
0!
b1011 %
b1011 Z
1"
0S
b100 \
1+
#150000
b10001101110110011001111011101 '
b10001101110110011001111011101 B
b10001 ,
b10001 A
0<
0?
0+
#151000
b1011 d
#155000
1&
0"
1+
#160000
0+
#165000
1+
#166000
1`
b1100 _
b1 ^
b1001000 ]
#170000
19
18
b1100 1
b1100 F
b1 2
b1 G
b1001000 .
b1001000 C
0+
#175000
0&
1!
1Y
b1100 V
b1 W
b1001000 T
1S
1+
#180000
0b
b1111 c
b10001000100010010001000100010 a
09
0+
#185000
1+
#190000
1?
b1111 =
b1111 M
b10001000100010010001000100010 ;
b10001000100010010001000100010 L
0+
#195000
b100 \
1+
#200000
1b
b110011001100110100010001000100 a
0?
0+
#205000
1+
#210000
1?
1<
b110011001100110100010001000100 ;
b110011001100110100010001000100 L
0+
#215000
0!
1#
b1100 %
b1100 Z
1"
0S
b100 \
1+
#220000
b110011001100110100010001000100 '
b110011001100110100010001000100 B
b10010 ,
b10010 A
0<
0?
0+
#221000
1f
b1100 d
#225000
1&
0"
1+
