rtl/axi_read_only/axi_read.v
// write axi read case
`timescale 1ns/1ps
module axi #(
    parameter ID_WIDTH = 4,
    parameter DATA_WIDTH = 32,
    parameter USER_WIDTH = 1
)(
    input wire clk,
    input wire rst,
    //=========================
    //AXI4 Read Address(AR) Channel
    //=========================
    input wire s_axi_arvalid,
    output wire s_axi_arready,
    input wire [31:0] s_axi_araddr,
    input wire [2:0] s_axi_arsize,
    input wire [1:0] s_axi_arburst,
    input wire [3:0] s_axi_arcache,
    input wire [2:0] s_axi_arprot,
    input wire [ID_WIDTH-1:0] s_axi_arid,
    //input wire [3:0] s_axi_arlen,    //AXI3
    input wire [7:0] s_axi_arlen,
    input wire s_axi_arlock,
    //input wire [1:0] s_axi_arlock,   //AXI3
    input wire [3:0] s_axi_arqos,
    input wire [3:0] s_axi_arregion,
    input wire [USER_WIDTH-1:0] s_axi_aruser,

    //=========================
    //AXI4 Read Data(R) Channel
    //=========================
    output reg s_axi_rvalid,
    input wire s_axi_rready,
    output reg s_axi_rlast,
    output reg [DATA_WIDTH-1:0] s_axi_rdata,
    output reg [1:0] s_axi_rresp,
    output reg [ID_WIDTH-1:0] s_axi_rid,
    output reg [USER_WIDTH-1:0] s_axi_ruser,

    //=========================
    //Debug Memory Interface
    //=========================
    output wire [DATA_WIDTH-1:0] debug_memory_data,
    input wire [7:0] debug_memory_addr
);

localparam integer MEMORY_DEPTH = 256;

reg [DATA_WIDTH-1:0] memory [0:MEMORY_DEPTH-1];

reg ar_active;
reg [31:0] araddr_reg;
reg [2:0] arsize_reg;
reg [1:0] arburst_reg;
reg [7:0] arlen_reg;
reg [ID_WIDTH-1:0] arid_reg;
reg [USER_WIDTH-1:0] aruser_reg;

//預先填入測試資料 for read tb
integer idx;
initial begin
    for (idx = 0; idx < MEMORY_DEPTH; idx = idx + 1) begin
        memory[idx] = 32'h0;
    end
    memory[8'd16] = 32'hAABB_CCDD; // 0x40 對應的 Word
    memory[8'd17] = 32'h11BB_33DD; // 0x44 對應的 Word
    memory[8'd18] = 32'h1111_2222; // 0x48 對應的 Word
    memory[8'd19] = 32'h3333_4444; // 0x4C 對應的 Word
end

assign s_axi_arready = !ar_active && !s_axi_rvalid;
assign debug_memory_data = memory[debug_memory_addr];

// AR & R Channel
always @(posedge clk) begin
    if (rst) begin
        ar_active <= 1'b0;
        araddr_reg <= 32'b0;
        arsize_reg <= 3'b0;
        arburst_reg <= 2'b0;
        arlen_reg <= 8'b0;
        arid_reg <= {ID_WIDTH{1'b0}};
        aruser_reg <= {USER_WIDTH{1'b0}};

        s_axi_rvalid <= 1'b0;
        s_axi_rdata <= {DATA_WIDTH{1'b0}};
        s_axi_rresp <= 2'b00;
        s_axi_rid <= {ID_WIDTH{1'b0}};
        s_axi_rlast <= 1'b0;
        s_axi_ruser <= {USER_WIDTH{1'b0}};
    end else begin

        // AR handshake
        if (s_axi_arvalid && s_axi_arready) begin
            ar_active <= 1'b1;
            araddr_reg <= s_axi_araddr;
            arsize_reg <= s_axi_arsize;
            arburst_reg <= s_axi_arburst;
            arlen_reg <= s_axi_arlen;
            arid_reg <= s_axi_arid;
            aruser_reg <= s_axi_aruser;

            s_axi_rvalid <= 1'b1;
            s_axi_rdata <= memory[s_axi_araddr[9:2]];
            s_axi_rresp <= 2'b00; //OKAY
            s_axi_rid <= s_axi_arid;
            s_axi_rlast <= 1'b1;
            s_axi_ruser <= s_axi_aruser;
        end

        // R handshake
        if (s_axi_rvalid && s_axi_rready) begin
            s_axi_rvalid <= 1'b0; 
            s_axi_rlast <= 1'b0;
            ar_active <= 1'b0;
        end

    end
end

endmodule

rtl/axi_read_only/tb_axi_read.v
`timescale 1ns/1ps

module tb_axi_read;

    localparam ID_WIDTH = 4;
    localparam DATA_WIDTH = 32;
    localparam USER_WIDTH = 1;

    reg clk;
    reg rst;

    // AR Channel
    reg s_axi_arvalid;
    wire s_axi_arready;
    reg [31:0] s_axi_araddr;
    reg [2:0] s_axi_arsize;
    reg [1:0] s_axi_arburst;
    reg [3:0] s_axi_arcache;
    reg [2:0] s_axi_arprot;
    reg [ID_WIDTH-1:0] s_axi_arid;
    reg [7:0] s_axi_arlen;
    reg s_axi_arlock;
    reg [3:0] s_axi_arqos;
    reg [3:0] s_axi_arregion;
    reg [USER_WIDTH-1:0] s_axi_aruser;

    // R Channel
    wire s_axi_rvalid;
    reg s_axi_rready;
    wire s_axi_rlast;
    wire [DATA_WIDTH-1:0] s_axi_rdata;
    wire [1:0] s_axi_rresp;
    wire [ID_WIDTH-1:0] s_axi_rid;
    wire [USER_WIDTH-1:0] s_axi_ruser;

    // Debug
    reg [7:0] debug_memory_addr;
    wire [DATA_WIDTH-1:0] debug_memory_data;

    integer errors;
    integer timeout;

    axi #(
        .ID_WIDTH(ID_WIDTH),
        .DATA_WIDTH(DATA_WIDTH),
        .USER_WIDTH(USER_WIDTH)
    ) dut (
        .clk(clk),
        .rst(rst),

        .s_axi_arvalid(s_axi_arvalid),
        .s_axi_arready(s_axi_arready),
        .s_axi_araddr(s_axi_araddr),
        .s_axi_arsize(s_axi_arsize),
        .s_axi_arburst(s_axi_arburst),
        .s_axi_arcache(s_axi_arcache),
        .s_axi_arprot(s_axi_arprot),
        .s_axi_arid(s_axi_arid),
        .s_axi_arlen(s_axi_arlen),
        .s_axi_arlock(s_axi_arlock),
        .s_axi_arqos(s_axi_arqos),
        .s_axi_arregion(s_axi_arregion),
        .s_axi_aruser(s_axi_aruser),

        .s_axi_rvalid(s_axi_rvalid),
        .s_axi_rready(s_axi_rready),
        .s_axi_rlast(s_axi_rlast),
        .s_axi_rdata(s_axi_rdata),
        .s_axi_rresp(s_axi_rresp),
        .s_axi_rid(s_axi_rid),
        .s_axi_ruser(s_axi_ruser),

        .debug_memory_addr(debug_memory_addr),
        .debug_memory_data(debug_memory_data)
    );

    always #5 clk = ~clk;

    task automatic check;
        input condition;
        input [255:0] message;
        begin
            if (condition !== 1'b1) begin
                $display("ERROR: %0s", message);
                errors = errors + 1;
            end else begin
                $display("PASS: %0s", message);
            end
        end
    endtask

    task automatic send_ar;
        input [31:0] address;
        input [7:0] length;
        input [1:0] burst;
        input [ID_WIDTH-1:0] id;
        begin
            @(negedge clk);
            s_axi_araddr  = address;
            s_axi_arsize  = 3'd2;
            s_axi_arburst = burst;
            s_axi_arlen   = length;
            s_axi_arid    = id;
            s_axi_aruser  = 1'b1;
            s_axi_arvalid = 1'b1;

            while (!s_axi_arready)
                @(posedge clk);

            @(posedge clk);
            @(negedge clk);
            s_axi_arvalid = 1'b0;
        end
    endtask

    task automatic receive_r;
        input [DATA_WIDTH-1:0] expected_data;
        input expected_last;
        input [ID_WIDTH-1:0] expected_id;
        begin
            timeout = 0;

            while (!s_axi_rvalid && timeout < 20) begin
                @(posedge clk);
                timeout = timeout + 1;
            end

            check(timeout < 20, "RVALID timeout");
            check(s_axi_rdata == expected_data, "RDATA mismatch");
            check(s_axi_rlast == expected_last, "RLAST mismatch");
            check(s_axi_rresp == 2'b00, "RRESP is not OKAY");
            check(s_axi_rid == expected_id, "RID mismatch");
            check(s_axi_ruser == 1'b1, "RUSER mismatch");

            @(negedge clk);
            s_axi_rready = 1'b1;

            @(posedge clk);

            @(negedge clk);
            s_axi_rready = 1'b0;
        end
    endtask

    task automatic read_memory_word;
        input [7:0] address;
        output [DATA_WIDTH-1:0] value;
        begin
            debug_memory_addr = address;
            #1;
            value = debug_memory_data;
        end
    endtask

    reg [DATA_WIDTH-1:0] read_value;

    initial begin
        $dumpfile("axi_read.vcd");
        $dumpvars(0, tb_axi_read);

        clk = 1'b0;
        rst = 1'b1;
        errors = 0;

        s_axi_arvalid = 1'b0;
        s_axi_rready = 1'b0;

        s_axi_araddr = 0;
        s_axi_arsize = 0;
        s_axi_arburst = 0;
        s_axi_arcache = 0;
        s_axi_arprot = 0;
        s_axi_arid = 0;
        s_axi_arlen = 0;
        s_axi_arlock = 0;
        s_axi_arqos = 0;
        s_axi_arregion = 0;
        s_axi_aruser = 0;

        debug_memory_addr = 0;

        repeat (2) @(posedge clk);
        rst = 1'b0;

        check(s_axi_arready, "ARREADY is not high after reset");

        // Test 1: 直接透過 debug port 驗證預設資料
        read_memory_word(8'd16, read_value);
        check(read_value == 32'hAABB_CCDD, "Preloaded memory word 16 mismatch");

        read_memory_word(8'd18, read_value);
        check(read_value == 32'h1111_2222, "Preloaded memory word 18 mismatch");

        // Test 2: Single-beat read (Address 0x48 -> Word 18)
        $display("--- Test 2: Read Address 0x48 ---");
        send_ar(32'h48, 8'd0, 2'b01, 4'h5);
        check(s_axi_rvalid, "RVALID should be high after AR handshake");
        check(s_axi_rdata == 32'h1111_2222, "Read beat 0 RDATA mismatch");
        check(s_axi_rlast, "Single-beat RLAST should be high");
        receive_r(32'h1111_2222, 1'b1, 4'h5);

        // Test 3: Single-beat read (Address 0x4C -> Word 19)
        $display("--- Test 3: Read Address 0x4C ---");
        send_ar(32'h4C, 8'd0, 2'b01, 4'h6);
        check(s_axi_rvalid, "RVALID should be high after AR handshake");
        check(s_axi_rdata == 32'h3333_4444, "Read beat 1 RDATA mismatch");
        check(s_axi_rlast, "Single-beat RLAST should be high");
        receive_r(32'h3333_4444, 1'b1, 4'h6);

        if (errors == 0)
            $display("PASS: AXI read testbench");
        else
            $display("FAIL: %0d error(s)", errors);

        #20;
        $finish;
    end

endmodule

rtl/axi_read_only/axi_read.vcd
$date
	Tue Sep 15 15:28:25 2026
$end
$version
	Icarus Verilog
$end
$timescale
	1ps
$end
$scope module tb_axi_read $end
$var wire 1 ! s_axi_rvalid $end
$var wire 1 " s_axi_ruser $end
$var wire 2 # s_axi_rresp [1:0] $end
$var wire 1 $ s_axi_rlast $end
$var wire 4 % s_axi_rid [3:0] $end
$var wire 32 & s_axi_rdata [31:0] $end
$var wire 1 ' s_axi_arready $end
$var wire 32 ( debug_memory_data [31:0] $end
$var parameter 32 ) DATA_WIDTH $end
$var parameter 32 * ID_WIDTH $end
$var parameter 32 + USER_WIDTH $end
$var reg 1 , clk $end
$var reg 8 - debug_memory_addr [7:0] $end
$var reg 32 . read_value [31:0] $end
$var reg 1 / rst $end
$var reg 32 0 s_axi_araddr [31:0] $end
$var reg 2 1 s_axi_arburst [1:0] $end
$var reg 4 2 s_axi_arcache [3:0] $end
$var reg 4 3 s_axi_arid [3:0] $end
$var reg 8 4 s_axi_arlen [7:0] $end
$var reg 1 5 s_axi_arlock $end
$var reg 3 6 s_axi_arprot [2:0] $end
$var reg 4 7 s_axi_arqos [3:0] $end
$var reg 4 8 s_axi_arregion [3:0] $end
$var reg 3 9 s_axi_arsize [2:0] $end
$var reg 1 : s_axi_aruser $end
$var reg 1 ; s_axi_arvalid $end
$var reg 1 < s_axi_rready $end
$var integer 32 = errors [31:0] $end
$var integer 32 > timeout [31:0] $end
$scope module dut $end
$var wire 1 , clk $end
$var wire 8 ? debug_memory_addr [7:0] $end
$var wire 32 @ debug_memory_data [31:0] $end
$var wire 1 / rst $end
$var wire 32 A s_axi_araddr [31:0] $end
$var wire 2 B s_axi_arburst [1:0] $end
$var wire 4 C s_axi_arcache [3:0] $end
$var wire 4 D s_axi_arid [3:0] $end
$var wire 8 E s_axi_arlen [7:0] $end
$var wire 1 5 s_axi_arlock $end
$var wire 3 F s_axi_arprot [2:0] $end
$var wire 4 G s_axi_arqos [3:0] $end
$var wire 1 ' s_axi_arready $end
$var wire 4 H s_axi_arregion [3:0] $end
$var wire 3 I s_axi_arsize [2:0] $end
$var wire 1 : s_axi_aruser $end
$var wire 1 ; s_axi_arvalid $end
$var wire 1 < s_axi_rready $end
$var parameter 32 J DATA_WIDTH $end
$var parameter 32 K ID_WIDTH $end
$var parameter 32 L MEMORY_DEPTH $end
$var parameter 32 M USER_WIDTH $end
$var reg 1 N ar_active $end
$var reg 32 O araddr_reg [31:0] $end
$var reg 2 P arburst_reg [1:0] $end
$var reg 4 Q arid_reg [3:0] $end
$var reg 8 R arlen_reg [7:0] $end
$var reg 3 S arsize_reg [2:0] $end
$var reg 1 T aruser_reg $end
$var reg 32 U s_axi_rdata [31:0] $end
$var reg 4 V s_axi_rid [3:0] $end
$var reg 1 $ s_axi_rlast $end
$var reg 2 W s_axi_rresp [1:0] $end
$var reg 1 " s_axi_ruser $end
$var reg 1 ! s_axi_rvalid $end
$var integer 32 X idx [31:0] $end
$upscope $end
$scope task check $end
$upscope $end
$scope task read_memory_word $end
$upscope $end
$scope task receive_r $end
$upscope $end
$scope task send_ar $end
$upscope $end
$upscope $end
$enddefinitions $end
$comment Show the parameter values. $end
$dumpall
b1 M
b100000000 L
b100 K
b100000 J
b1 +
b100 *
b100000 )
$end
#0
$dumpvars
b100000000 X
bx W
bx V
bx U
xT
bx S
bx R
bx Q
bx P
bx O
xN
b0 I
b0 H
b0 G
b0 F
b0 E
b0 D
b0 C
b0 B
b0 A
b0 @
b0 ?
bx >
b0 =
0<
0;
0:
b0 9
b0 8
b0 7
b0 6
05
b0 4
b0 3
b0 2
b0 1
b0 0
1/
bx .
b0 -
0,
b0 (
x'
bx &
bx %
x$
bx #
x"
x!
$end
#5000
1'
0"
0$
b0 %
b0 V
b0 #
b0 W
b0 &
b0 U
0!
0T
b0 Q
b0 R
b0 P
b0 S
b0 O
0N
1,
#10000
0,
#15000
b10101010101110111100110011011101 (
b10101010101110111100110011011101 @
b10000 -
b10000 ?
0/
1,
#16000
b10001000100010010001000100010 (
b10001000100010010001000100010 @
b10010 -
b10010 ?
b10101010101110111100110011011101 .
#17000
b10001000100010010001000100010 .
#20000
1;
1:
b101 3
b101 D
b1 1
b1 B
b10 9
b10 I
b1001000 0
b1001000 A
0,
#25000
0'
1"
1$
b101 %
b101 V
b10001000100010010001000100010 &
b10001000100010010001000100010 U
1!
1T
b101 Q
b1 P
b10 S
b1001000 O
1N
1,
#30000
b0 >
0;
0,
#35000
1,
#40000
1<
0,
#45000
1'
0N
0$
0!
1,
#50000
0<
0,
#55000
1,
#60000
1;
b110 3
b110 D
b1001100 0
b1001100 A
0,
#65000
0'
1$
b110 %
b110 V
b110011001100110100010001000100 &
b110011001100110100010001000100 U
1!
b110 Q
b1001100 O
1N
1,
#70000
0;
0,
#75000
1,
#80000
1<
0,
#85000
1'
0N
0$
0!
1,
#90000
0<
0,
